cvgen/__init__.py
cvgen/main.py
cvgen/models.py
cvgen/templates/index.html.j2
cvgen/templates/style.css
cvgen-0.5.0.dist-info/LICENSE
cvgen-0.5.0.dist-info/METADATA
cvgen-0.5.0.dist-info/WHEEL
cvgen-0.5.0.dist-info/entry_points.txt
cvgen-0.5.0.dist-info/RECORD
