Metadata-Version: 2.1
Name: cvgen
Version: 0.5.0
Summary: A tool for easily creating a good-looking CV in PDF format from .yaml data, HTML & CSS.
Author: Vadim Galaktionov
Author-email: vadim@galaktionov.nl
Requires-Python: >=3.11,<4.0
Classifier: Programming Language :: Python :: 3
Classifier: Programming Language :: Python :: 3.11
Classifier: Programming Language :: Python :: 3.12
Classifier: Programming Language :: Python :: 3.13
Requires-Dist: click (>=8.1.7,<9.0.0)
Requires-Dist: email-validator (>=2.0,<3.0)
Requires-Dist: jinja2 (>=3.1.4,<4.0.0)
Requires-Dist: pydantic (>=2.9.2,<3.0.0)
Requires-Dist: pyyaml (>=5.1,<5.4)
Requires-Dist: weasyprint (>=62.3,<63.0)
